zenray/__init__.py
zenray/candidates.py
zenray/client.py
zenray/config.py
zenray/context.py
zenray/decorators.py
zenray/helpers.py
zenray/models.py
zenray/py.typed
zenray/run.py
zenray/step_legacy.py
zenray-0.2.0.dist-info/METADATA
zenray-0.2.0.dist-info/WHEEL
zenray-0.2.0.dist-info/licenses/LICENSE
zenray-0.2.0.dist-info/RECORD
