Metadata-Version: 2.4
Name: zenray
Version: 0.2.0
Summary: Observability SDK for ML/LLM pipelines - debug candidate drop-off and track decision context
Project-URL: Homepage, https://zenray.live
Project-URL: Documentation, https://zenray.live/docs
Project-URL: Repository, https://github.com/DeepakSilaych/ZenRay
Project-URL: Issues, https://github.com/DeepakSilaych/ZenRay/issues
Project-URL: Changelog, https://github.com/DeepakSilaych/ZenRay/blob/main/CHANGELOG.md
Author-email: Deepak Silaych <deepaksilaych@gmail.com>
Maintainer-email: Deepak Silaych <deepaksilaych@gmail.com>
License: MIT
License-File: LICENSE
Keywords: debugging,instrumentation,llm,ml,monitoring,observability,pipelines,rag,tracing
Classifier: Development Status :: 4 - Beta
Classifier: Intended Audience :: Developers
Classifier: Intended Audience :: Science/Research
Classifier: License :: OSI Approved :: MIT License
Classifier: Operating System :: OS Independent
Classifier: Programming Language :: Python :: 3
Classifier: Programming Language :: Python :: 3.9
Classifier: Programming Language :: Python :: 3.10
Classifier: Programming Language :: Python :: 3.11
Classifier: Programming Language :: Python :: 3.12
Classifier: Topic :: Scientific/Engineering :: Artificial Intelligence
Classifier: Topic :: Software Development :: Debuggers
Classifier: Topic :: System :: Monitoring
Classifier: Typing :: Typed
Requires-Python: >=3.9
Requires-Dist: httpx>=0.24.0
Requires-Dist: pydantic>=2.0.0
Provides-Extra: dev
Requires-Dist: mypy>=1.0.0; extra == 'dev'
Requires-Dist: pytest-asyncio>=0.21.0; extra == 'dev'
Requires-Dist: pytest>=7.0.0; extra == 'dev'
Requires-Dist: ruff>=0.1.0; extra == 'dev'
